[{
	"name": "image1",
	"url": "/src/assets/images/z1.jpg"
}, {
	"name": "image2",
	"url": "/src/assets/images/z2.jpg"
}, {
	"name": "image3",
	"url": "/src/assets/images/z3.jpg"
}, {
	"name": "image4",
	"url": "/src/assets/images/z4.jpg"
}, {
	"name": "image5",
	"url": "/src/assets/images/z5.jpg"
}, {
	"name": "image6",
	"url": "/src/assets/images/z6.jpg"
}, {
	"name": "image7",
	"url": "/src/assets/images/z7.jpg"
}, {
	"name": "image8",
	"url": "/src/assets/images/z8.jpg"
}, {
	"name": "image9",
	"url": "/src/assets/images/z9.jpg"
}, {
	"name": "image10",
	"url": "/src/assets/images/z10.jpg"
}, {
	"name": "image11",
	"url": "/src/assets/images/z11.jpg"
}, {
	"name": "image12",
	"url": "/src/assets/images/z12.jpg"
}, {
	"name": "image13",
	"url": "/src/assets/images/z13.jpg"
}, {
	"name": "image14",
	"url": "/src/assets/images/z14.jpg"
}, {
	"name": "image15",
	"url": "/src/assets/images/z15.jpg"
}, {
	"name": "image16",
	"url": "/src/assets/images/z16.jpg"
}]